README.rst
setup.py
src/sentry_slack_integration_webhooks/__init__.py
src/sentry_slack_integration_webhooks/models.py
src/sentry_slack_integration_webhooks/plugin.py
src/sentry_slack_integration_webhooks.egg-info/PKG-INFO
src/sentry_slack_integration_webhooks.egg-info/SOURCES.txt
src/sentry_slack_integration_webhooks.egg-info/dependency_links.txt
src/sentry_slack_integration_webhooks.egg-info/entry_points.txt
src/sentry_slack_integration_webhooks.egg-info/not-zip-safe
src/sentry_slack_integration_webhooks.egg-info/requires.txt
src/sentry_slack_integration_webhooks.egg-info/top_level.txt